topsis_purvi05/__init__.py
topsis_purvi05/topsis.py
topsis_purvi05-0.0.1.dist-info/METADATA
topsis_purvi05-0.0.1.dist-info/WHEEL
topsis_purvi05-0.0.1.dist-info/top_level.txt
topsis_purvi05-0.0.1.dist-info/RECORD
