Metadata-Version: 2.1
Name: topsis-purvi05
Version: 0.0.1
Summary: topsis implementation
Home-page: UNKNOWN
Author: PURVI KANANI
Author-email: purvi5kanani@gmail.com
License: MIT
Keywords: topsis,topsis implementation
Platform: UNKNOWN
Classifier: Development Status :: 3 - Alpha
Classifier: Intended Audience :: Developers
Classifier: Topic :: Software Development :: Build Tools
Classifier: License :: OSI Approved :: MIT License
Classifier: Programming Language :: Python :: 3
Classifier: Programming Language :: Python :: 3.4
Classifier: Programming Language :: Python :: 3.5
Classifier: Programming Language :: Python :: 3.6
Classifier: Programming Language :: Python :: 3.6
Requires-Dist: numpy
